<?xml version="1.0" encoding="UTF-8"?>
<site>
   <feature url="features/info.evanchik.eclipse.karaf.feature_0.5.0.201002072229.jar" id="info.evanchik.eclipse.karaf.feature" version="0.5.0.201002072229">
      <category name="info.evanchik.eclipse.karaf"/>
   </feature>
   <feature url="features/info.evanchik.eclipse.karaf.jmx.feature_0.5.0.201002072229.jar" id="info.evanchik.eclipse.karaf.jmx.feature" version="0.5.0.201002072229">
      <category name="info.evanchik.eclipse.karaf"/>
   </feature>
   <feature url="features/info.evanchik.smk.feature_0.5.0.201002072229.jar" id="info.evanchik.smk.feature" version="0.5.0.201002072229">
      <category name="info.evanchik.eclipse.smk"/>
   </feature>
   <category-def name="info.evanchik.eclipse.karaf" label="Eclipse Integration for Apache Felix Karaf"/>
   <category-def name="info.evanchik.eclipse.smk" label="Eclipse Integration for Apache ServiceMix Kernel"/>
</site>
